mhd_api/__init__.py
mhd_api/mhd.py
mhd_api-0.2.dist-info/LICENSE.TXT
mhd_api-0.2.dist-info/METADATA
mhd_api-0.2.dist-info/WHEEL
mhd_api-0.2.dist-info/top_level.txt
mhd_api-0.2.dist-info/RECORD
