Metadata-Version: 2.1
Name: mhd-api
Version: 0.2
Summary: Used to get data about Bratislava MHD
Home-page: https://github.com/mrtineu
Download-URL: https://github.com/mrtineu/MHD_API/archive/refs/tags/0.2.tar.gz
Author: MrTinEU
Author-email: mrtineu416@gmail.com
License: MIT
Keywords: API,MHD,BUS,Bratislava
Classifier: Development Status :: 5 - Production/Stable
Classifier: Intended Audience :: Developers
Classifier: Topic :: Software Development :: Build Tools
Classifier: License :: OSI Approved :: MIT License
Classifier: Programming Language :: Python :: 3
Classifier: Programming Language :: Python :: 3.4
Classifier: Programming Language :: Python :: 3.5
Classifier: Programming Language :: Python :: 3.6
License-File: LICENSE.TXT
Requires-Dist: requests
